re_static/__init__.py
re_static/analyzer.py
re_static/py.typed
re_static/re_static.py
re_static/types.py
re_static/mypy_plugin/__init__.py
re_static/mypy_plugin/plugin.py
re_static-0.1.0.dist-info/METADATA
re_static-0.1.0.dist-info/WHEEL
re_static-0.1.0.dist-info/entry_points.txt
re_static-0.1.0.dist-info/licenses/LICENSE
re_static-0.1.0.dist-info/RECORD
