Metadata-Version: 2.4
Name: re-static
Version: 0.1.0
Summary: Safe boilerplate-free static regular expressions with MyPy support
Project-URL: Repository, https://github.com/mingaleg/re-static
Author-email: Oleg Mingalev <oleg@mingalev.net>
License-Expression: MIT
License-File: LICENSE
Classifier: Development Status :: 4 - Beta
Classifier: Intended Audience :: Developers
Classifier: Operating System :: OS Independent
Classifier: Programming Language :: Python
Classifier: Programming Language :: Python :: 3
Classifier: Programming Language :: Python :: 3.11
Classifier: Programming Language :: Python :: 3.12
Classifier: Programming Language :: Python :: 3.13
Classifier: Typing :: Typed
Requires-Python: <4.0,>=3.11
Requires-Dist: mypy>=1.18.2
